ColorizerAJM/__init__.py
ColorizerAJM/_version.py
ColorizerAJM/base_classes.py
ColorizerAJM/colorizer.py
ColorizerAJM/custom_colors.py
ColorizerAJM/errs.py
colorizerajm-0.5.dist-info/licenses/LICENSE.txt
colorizerajm-0.5.dist-info/METADATA
colorizerajm-0.5.dist-info/WHEEL
colorizerajm-0.5.dist-info/top_level.txt
colorizerajm-0.5.dist-info/RECORD
