Metadata-Version: 2.4
Name: ColorizerAJM
Version: 0.5
Summary: Taken from https://medium.com/@ryan_forrester_/adding-color-to-python-terminal-output-a-complete-guide-147fcb1c335f uses ANSI escape codes to colorize terminal output
Home-page: https://github.com/amcsparron2793-Water/ColorizerAJM
Download-URL: https://github.com/amcsparron2793-Water/ColorizerAJM/archive/refs/tags/0.5.tar.gz
Author: Amcsparron
Author-email: amcsparron@albanyny.gov
License: MIT License
Classifier: Development Status :: 4 - Beta
Classifier: Intended Audience :: Developers
Classifier: Topic :: Software Development :: Build Tools
Classifier: License :: OSI Approved :: MIT License
Classifier: Programming Language :: Python :: 3
License-File: LICENSE.txt
Dynamic: author
Dynamic: author-email
Dynamic: classifier
Dynamic: download-url
Dynamic: home-page
Dynamic: license
Dynamic: license-file
Dynamic: summary
